.gitignore
.travis.yml
CHANGELOG.md
LICENSE
MANIFEST.in
README.md
requirements.txt
run-tests.sh
setup.py
virtualenv.py
src/django_fields/__init__.py
src/django_fields/fields.py
src/django_fields/models.py
src/django_fields/tests.py
src/django_fields.egg-info/PKG-INFO
src/django_fields.egg-info/SOURCES.txt
src/django_fields.egg-info/dependency_links.txt
src/django_fields.egg-info/requires.txt
src/django_fields.egg-info/top_level.txt
src/example/__init__.py
src/example/manage.py
src/example/settings.py
src/example/urls.py
src/example/blog/__init__.py
src/example/blog/admin.py
src/example/blog/models.py