Metadata-Version: 1.0
Name: django-fields
Version: 0.3.0
Summary: Django-fields is an application which includes different kinds of models fields.
Home-page: http://github.com/svetlyak40wt/django-fields/
Author: Alexander Artemenko
Author-email: svetlyak.40wt@gmail.com
License: New BSD License
Keywords: django apps tools collection
Platform: UNKNOWN
Classifier: Development Status :: 2 - Pre-Alpha
Classifier: Environment :: Plugins
Classifier: Framework :: Django
Classifier: Intended Audience :: Developers
Classifier: License :: OSI Approved :: BSD License
Classifier: Programming Language :: Python
Classifier: Topic :: Software Development :: Libraries :: Python Modules
